spawnlabs/__init__.py
spawnlabs/cli.py
spawnlabs/ui.py
spawnlabs-0.1.0.dist-info/licenses/LICENSE
spawnlabs-0.1.0.dist-info/METADATA
spawnlabs-0.1.0.dist-info/WHEEL
spawnlabs-0.1.0.dist-info/entry_points.txt
spawnlabs-0.1.0.dist-info/top_level.txt
spawnlabs-0.1.0.dist-info/RECORD
