Metadata-Version: 2.4
Name: spawnlabs
Version: 0.1.0
Summary: Intelligent platform for building, running, and maintaining autonomous systems
Home-page: https://spawnlabs.ai
Author: SpawnLabs
Author-email: SpawnLabs <contact@spawnlabs.ai>
Project-URL: Homepage, https://spawnlabs.ai
Project-URL: Documentation, https://spawnlabs.ai/docs
Project-URL: Repository, https://github.com/teddyoweh/spawn-frontend-temp
Project-URL: Bug Tracker, https://github.com/teddyoweh/spawn-frontend-temp/issues
Keywords: frontend,ui,development,ai,spawn,spawnlabs
Classifier: Development Status :: 3 - Alpha
Classifier: Intended Audience :: Developers
Classifier: Topic :: Software Development :: Build Tools
Classifier: Topic :: Software Development :: Code Generators
Classifier: License :: OSI Approved :: MIT License
Classifier: Programming Language :: Python :: 3
Classifier: Programming Language :: Python :: 3.7
Classifier: Programming Language :: Python :: 3.8
Classifier: Programming Language :: Python :: 3.9
Classifier: Programming Language :: Python :: 3.10
Classifier: Programming Language :: Python :: 3.11
Classifier: Programming Language :: Python :: 3.12
Classifier: Operating System :: OS Independent
Requires-Python: >=3.7
License-File: LICENSE
Dynamic: author
Dynamic: home-page
Dynamic: license-file
Dynamic: requires-python
